{
  "cursos": [
    {
      "id": 1,
      "nome": "Angular16"
    },
    {
      "id": 2,
      "nome": ".NET6"
    },
    {
      "nome": "Java",
      "id": 3
    },
    {
      "nome": "MySQL",
      "id": 4
    },
    {
      "nome": "C#",
      "id": 5
    },
    {
      "nome": "Bootstrap4",
      "id": 6
    },
    {
      "nome": "PHP",
      "id": 7
    },
    {
      "nome": "HTML e CSS",
      "id": 8
    },
    {
      "nome": "ASP.Net",
      "id": 9
    },
    {
      "id": 10,
      "nome": "Ruby"
    }
  ]
}